ercot/__init__.py
ercot/rts.py
ercot_rts-2023.8.1.dist-info/METADATA
ercot_rts-2023.8.1.dist-info/WHEEL
ercot_rts-2023.8.1.dist-info/top_level.txt
ercot_rts-2023.8.1.dist-info/RECORD
