Metadata-Version: 2.1
Name: ercot-rts
Version: 2023.8.1
Summary: ERCOT Realtime Settlement Library
Author: tafypz
License: Apache-2.0
Project-URL: repository, https://github.com/tafypz/ercot_rts.git
Keywords: energy
Classifier: Development Status :: 5 - Production/Stable
Classifier: Intended Audience :: End Users/Desktop
Classifier: Intended Audience :: Developers
Classifier: License :: OSI Approved :: Apache Software License
Classifier: Operating System :: OS Independent
Classifier: Programming Language :: Python :: 3.11
Classifier: Topic :: Software Development
Requires-Python: >=3.11.0
Requires-Dist: beautifulsoup4 >=4.12.2
Requires-Dist: requests >=2.31.0
